{"data": {"event": {"id": "1919f2b2-6029-45bd-816b-b1fdc713bfd7", "picture": "https://services.medicalcongress.online/congress/medias/2024/JFR2024/670/video/thumbs/poster.jpg", "sessionType": "Séance scientifique", "sessionTypeColor": "#44fc54", "voting": null, "title": "Séance de communications orales en innovations et recherche", "start": "2024-10-06T14:00+02:00", "end": "2024-10-06T15:15+02:00", "objectives": ["<p>A la fin de la séance les congressistes seront en mesure de&nbsp;:&nbsp;</p>", "<p>Connaître les innovations et les avancées scientifiques en imagerie&nbsp;</p>"], "onAir": null, "vod": {"checkPermissions": ["media:view"], "media": null}, "broadcasts": {"items": []}, "room": {"id": "f4c04ae0-ad5a-4230-896c-2a8dd9ef7a9e", "name": "Salle Passy", "type": "ROOM"}, "schedule": {"items": [{"id": "2b8697b9-a2eb-4c2e-9361-c36fec92ddb2", "title": "Développement et évaluation d'un fantôme IRM par impression 3D dédié à l'enseignement", "start": "2024-10-06T14:00+02:00", "end": "2024-10-06T14:09+02:00", "element": {"abstract": {"id": "D2F14B6E-3251-4D5B-A6B5-3A77FD3CD0D4"}}, "speakers": {"items": [{"id": "2b69e969-0fed-47c9-b16d-37b48b94ee15", "lastName": "Dillenseger", "firstName": "Jean-Philippe", "roles": [{"name": "speaker"}], "photo": {"url": "https://services.y-congress.com/congress/wspreview/getphoto.aspx?idPhoto=177473&t=1"}, "country": {"name": "France"}, "city": {"name": "Strasbourg"}}]}, "vod": {"checkPermissions": ["media:view"], "media": {"id": "5bdb5f5e-6fe5-4940-9a62-d91d9a546f7d", "type": "VIDEO", "thumbnail": "https://services.medicalcongress.online/congress/medias/2024/JFR2024/669/video/thumbs/poster.jpg", "element": {"sources": [{"uri": "https://services.medicalcongress.online/congress/medias/2024/JFR2024/669/video/y_1080p_4000kb.mp4"}, {"uri": "https://services.medicalcongress.online/congress/medias/2024/JFR2024/669/video/y_480p_800kb.mp4"}]}}}}, {"id": "2eb27582-d359-4b9c-99ff-4ebc50ac8509", "title": "Biomarqueurs de la dépression en IRM de diffusion à partir des graphes de connectivité cérébrale", "start": "2024-10-06T14:09+02:00", "end": "2024-10-06T14:18+02:00", "element": {"abstract": {"id": "83D09B92-3F8C-4B15-8335-966239D72129"}}, "speakers": {"items": [{"id": "eafe6ac2-acff-4e07-967b-7b2dc695745e", "lastName": "Ramon", "firstName": "François", "roles": [{"name": "speaker"}], "photo": null, "country": {"name": "France"}, "city": {"name": "Paris"}}]}, "vod": {"checkPermissions": ["media:view"], "media": {"id": "39fb8659-facb-412d-be79-e4fddb406ebe", "type": "VIDEO", "thumbnail": "https://services.medicalcongress.online/congress/medias/2024/JFR2024/670/video/thumbs/poster.jpg", "element": {"sources": [{"uri": "https://services.medicalcongress.online/congress/medias/2024/JFR2024/670/video/y_1080p_4000kb.mp4"}, {"uri": "https://services.medicalcongress.online/congress/medias/2024/JFR2024/670/video/y_480p_800kb.mp4"}]}}}}, {"id": "9fb201de-dca6-440e-9436-958da57e1afe", "title": "Visualization of Renal Glomeruli in Human Native Kidneys With Sensing Ultrasound Localization Microscopy", "start": "2024-10-06T14:18+02:00", "end": "2024-10-06T14:27+02:00", "element": {"abstract": {"id": "11070673-E0AA-4859-B250-5535B37E0A6C"}}, "speakers": {"items": [{"id": "40301093-9f9c-424c-b2be-8aa59e648adf", "lastName": "Bodard", "firstName": "Sylvain", "roles": [{"name": "speaker"}], "photo": {"url": "https://services.y-congress.com/congress/wspreview/getphoto.aspx?idPhoto=177570&t=1"}, "country": {"name": "France"}, "city": {"name": "Paris"}}]}, "vod": {"checkPermissions": ["media:view"], "media": {"id": "a6a3a9c1-1755-4482-b330-14b11fe19264", "type": "VIDEO", "thumbnail": "https://services.medicalcongress.online/congress/medias/2024/JFR2024/671/video/thumbs/poster.jpg", "element": {"sources": [{"uri": "https://services.medicalcongress.online/congress/medias/2024/JFR2024/671/video/y_1080p_4000kb.mp4"}, {"uri": "https://services.medicalcongress.online/congress/medias/2024/JFR2024/671/video/y_480p_800kb.mp4"}]}}}}, {"id": "ce26b232-3784-4fe6-aeca-eb8217ba5479", "title": "Réutilisation des données de santé pour le développement d’outils à valeur ajoutée pour la radiologie", "start": "2024-10-06T14:27+02:00", "end": "2024-10-06T14:36+02:00", "element": {"abstract": {"id": "FE1EDD99-616F-4268-8B9D-F6D810CFB935"}}, "speakers": {"items": [{"id": "2a96a525-a577-4816-b261-2153500e0082", "lastName": "Roche", "firstName": "Stephane", "roles": [{"name": "speaker"}], "photo": {"url": "https://services.y-congress.com/congress/wspreview/getphoto.aspx?idPhoto=174081&t=1"}, "country": {"name": "France"}, "city": {"name": "Marseille"}}]}, "vod": {"checkPermissions": ["media:view"], "media": {"id": "9e440581-4ac3-4616-b3a4-22eb1564920a", "type": "VIDEO", "thumbnail": "https://services.medicalcongress.online/congress/medias/2024/JFR2024/672/video/thumbs/poster.jpg", "element": {"sources": [{"uri": "https://services.medicalcongress.online/congress/medias/2024/JFR2024/672/video/y_1080p_4000kb.mp4"}, {"uri": "https://services.medicalcongress.online/congress/medias/2024/JFR2024/672/video/y_480p_800kb.mp4"}]}}}}, {"id": "d9b81eff-a9e0-4a9d-87e8-afc92a6c743a", "title": "Performance estimation of the french breast cancer screening program using the SNDS and DOCS database", "start": "2024-10-06T14:36+02:00", "end": "2024-10-06T14:45+02:00", "element": {"abstract": {"id": "D2AEA675-8714-4D60-BF40-FBEFD58A633D"}}, "speakers": {"items": [{"id": "43674da3-5106-47e1-a438-4f8bad89c672", "lastName": "Jemelen", "firstName": "Emilien", "roles": [{"name": "speaker"}], "photo": null, "country": {"name": "France"}, "city": {"name": "Paris"}}, {"id": "6e47d923-a5f9-4cb6-8300-83fb5a0cf492", "lastName": "Mares", "firstName": "Pierre", "roles": [{"name": "speaker"}], "photo": null, "country": {"name": "France"}, "city": {"name": "Carcassonne"}}]}, "vod": {"checkPermissions": ["media:view"], "media": {"id": "91f8ccae-e18f-4a47-a443-dc886ed36c50", "type": "VIDEO", "thumbnail": "https://services.medicalcongress.online/congress/medias/2024/JFR2024/673/video/thumbs/poster.jpg", "element": {"sources": [{"uri": "https://services.medicalcongress.online/congress/medias/2024/JFR2024/673/video/y_1080p_4000kb.mp4"}, {"uri": "https://services.medicalcongress.online/congress/medias/2024/JFR2024/673/video/y_480p_800kb.mp4"}]}}}}, {"id": "b15cfec0-0dfd-405d-8624-49d60e2349b2", "title": "De l’IRM qualitatif vers l’IRM quantitatif grâce à l’histogram matching", "start": "2024-10-06T14:45+02:00", "end": "2024-10-06T14:54+02:00", "element": {"abstract": {"id": "6BFD0205-1FDE-44C8-9CB8-B96855540D09"}}, "speakers": {"items": [{"id": "da6adabe-20af-4a75-bc05-53203f26ebef", "lastName": "Herpe", "firstName": "Guillaume", "roles": [{"name": "speaker"}], "photo": {"url": "https://services.y-congress.com/congress/wspreview/getphoto.aspx?idPhoto=177517&t=1"}, "country": {"name": "France"}, "city": {"name": "Poitiers"}}, {"id": "c2493a5e-e22d-4af4-9c73-ab8762364f9f", "lastName": "Billaud", "firstName": "Eliot", "roles": [{"name": "speaker"}], "photo": {"url": "https://services.y-congress.com/congress/wspreview/getphoto.aspx?idPhoto=177386&t=1"}, "country": {"name": "France"}, "city": {"name": "Poitiers"}}]}, "vod": {"checkPermissions": ["media:view"], "media": {"id": "10cc729f-3ae9-415c-b236-0fab55df725d", "type": "VIDEO", "thumbnail": "https://services.medicalcongress.online/congress/medias/2024/JFR2024/674/video/thumbs/poster.jpg", "element": {"sources": [{"uri": "https://services.medicalcongress.online/congress/medias/2024/JFR2024/674/video/y_1080p_4000kb.mp4"}, {"uri": "https://services.medicalcongress.online/congress/medias/2024/JFR2024/674/video/y_480p_800kb.mp4"}]}}}}, {"id": "862faa2d-dad1-4809-b435-3269d4c42c8d", "title": "Evaluation du rehaussement de moelle osseuse au scanner spectral double couche par cartes monoénergétiques 40keV", "start": "2024-10-06T14:54+02:00", "end": "2024-10-06T15:03+02:00", "element": {"abstract": {"id": "22A05A12-8FB5-4AE2-8879-7380AA2AE327"}}, "speakers": {"items": [{"id": "46e7a237-3f29-47e5-bc5d-d11db90b89a8", "lastName": "Grijseels", "firstName": "Stephane", "roles": [{"name": "speaker"}], "photo": {"url": "https://services.y-congress.com/congress/wspreview/getphoto.aspx?idPhoto=174082&t=1"}, "country": {"name": "France"}, "city": {"name": "Charleville-Mézières"}}]}, "vod": {"checkPermissions": ["media:view"], "media": {"id": "9d749f59-39f0-42f8-a842-b15f20905220", "type": "VIDEO", "thumbnail": "https://services.medicalcongress.online/congress/medias/2024/JFR2024/675/video/thumbs/poster.jpg", "element": {"sources": [{"uri": "https://services.medicalcongress.online/congress/medias/2024/JFR2024/675/video/y_1080p_4000kb.mp4"}, {"uri": "https://services.medicalcongress.online/congress/medias/2024/JFR2024/675/video/y_480p_800kb.mp4"}]}}}}]}, "roles": [{"name": "modérateur", "assignees": {"items": [{"id": "3d67610b-5c97-40e1-bea5-8a573e7afd56", "firstName": "Sébastien", "lastName": "Mulé", "photo": {"url": "https://services.y-congress.com/congress/wspreview/getphoto.aspx?idPhoto=173684&t=1"}, "country": {"name": "France"}, "city": {"name": "Créteil"}}, {"id": "b21fcbc3-db06-48d2-80a5-9855a1d11cb3", "firstName": "Catherine", "lastName": "Oppenheim", "photo": {"url": "https://services.y-congress.com/congress/wspreview/getphoto.aspx?idPhoto=177181&t=1"}, "country": {"name": "France"}, "city": {"name": "Paris"}}]}}, {"name": "responsable", "assignees": {"items": [{"id": "3d67610b-5c97-40e1-bea5-8a573e7afd56", "firstName": "Sébastien", "lastName": "Mulé", "photo": {"url": "https://services.y-congress.com/congress/wspreview/getphoto.aspx?idPhoto=173684&t=1"}, "country": {"name": "France"}, "city": {"name": "Créteil"}}, {"id": "b21fcbc3-db06-48d2-80a5-9855a1d11cb3", "firstName": "Catherine", "lastName": "Oppenheim", "photo": {"url": "https://services.y-congress.com/congress/wspreview/getphoto.aspx?idPhoto=177181&t=1"}, "country": {"name": "France"}, "city": {"name": "Paris"}}]}}], "speakers": {"items": [{"id": "2b69e969-0fed-47c9-b16d-37b48b94ee15", "firstName": "Jean-Philippe", "lastName": "Dillenseger", "photo": {"url": "https://services.y-congress.com/congress/wspreview/getphoto.aspx?idPhoto=177473&t=1"}, "country": {"name": "France"}, "city": {"name": "Strasbourg"}}, {"id": "eafe6ac2-acff-4e07-967b-7b2dc695745e", "firstName": "François", "lastName": "Ramon", "photo": null, "country": {"name": "France"}, "city": {"name": "Paris"}}, {"id": "40301093-9f9c-424c-b2be-8aa59e648adf", "firstName": "Sylvain", "lastName": "Bodard", "photo": {"url": "https://services.y-congress.com/congress/wspreview/getphoto.aspx?idPhoto=177570&t=1"}, "country": {"name": "France"}, "city": {"name": "Paris"}}, {"id": "2a96a525-a577-4816-b261-2153500e0082", "firstName": "Stephane", "lastName": "Roche", "photo": {"url": "https://services.y-congress.com/congress/wspreview/getphoto.aspx?idPhoto=174081&t=1"}, "country": {"name": "France"}, "city": {"name": "Marseille"}}, {"id": "43674da3-5106-47e1-a438-4f8bad89c672", "firstName": "Emilien", "lastName": "Jemelen", "photo": null, "country": {"name": "France"}, "city": {"name": "Paris"}}, {"id": "da6adabe-20af-4a75-bc05-53203f26ebef", "firstName": "Guillaume", "lastName": "Herpe", "photo": {"url": "https://services.y-congress.com/congress/wspreview/getphoto.aspx?idPhoto=177517&t=1"}, "country": {"name": "France"}, "city": {"name": "Poitiers"}}, {"id": "46e7a237-3f29-47e5-bc5d-d11db90b89a8", "firstName": "Stephane", "lastName": "Grijseels", "photo": {"url": "https://services.y-congress.com/congress/wspreview/getphoto.aspx?idPhoto=174082&t=1"}, "country": {"name": "France"}, "city": {"name": "Charleville-Mézières"}}, {"id": "6e47d923-a5f9-4cb6-8300-83fb5a0cf492", "firstName": "Pierre", "lastName": "Mares", "photo": null, "country": {"name": "France"}, "city": {"name": "Carcassonne"}}, {"id": "c2493a5e-e22d-4af4-9c73-ab8762364f9f", "firstName": "Eliot", "lastName": "Billaud", "photo": {"url": "https://services.y-congress.com/congress/wspreview/getphoto.aspx?idPhoto=177386&t=1"}, "country": {"name": "France"}, "city": {"name": "Poitiers"}}]}, "chairs": {"items": []}, "topics": [{"_id": "930d86a5-0a75-4354-827d-6a54fab5e47c", "value": "Innovations & Recherche"}], "tracks": [{"color": "#23b82a", "id": "e2ab05a5-4319-4577-9397-18f346d63319", "value": "Débutant", "label": "Débutant"}], "organizers": [{"id": "989b308e-ebe3-4d7f-ab1a-66c74f9898d1", "name": "Comité Recherche SFR-CERF", "logo": null}], "programmeOwners": [{"title": "JFR 2024", "id": "f611ad8b-1aa6-4e86-a968-fd38789b105e"}, {"title": "Physiciens médicaux", "id": "c5d61e43-7703-4174-b350-cae01637ed8d"}]}}}