{"data": {"event": {"id": "4850fb5b-d8ad-4c75-8f94-652e3544dba4", "picture": null, "title": "Prenez votre shot de science avec Juisci !", "start": "2024-10-04T11:00+02:00", "end": "2024-10-04T11:10+02:00", "objectives": [], "vod": null, "schedule": {"items": []}, "roles": [], "speakers": {"items": []}, "chairs": {"items": []}, "topics": [{"value": "Innovations & Recherche"}], "tracks": [], "organizers": [{"name": "Juisci", "logo": null}], "programmeOwners": [{"title": "JFR 2024"}, {"title": "Jeunes Radiologues"}]}}}