{"data": {"event": {"id": "de6df7b6-652c-40b4-b873-c6b71add44b7", "picture": "https://services.medicalcongress.online/congress/medias/2024/JFR2024/1985/video/thumbs/poster.jpg", "title": "Symposium Focus SIEMENS - Une collaboration étroite entre le professionnel de santé et l’industriel lors de la mise en place des innovations au service du patient", "start": "2024-10-05T13:15+02:00", "end": "2024-10-05T13:45+02:00", "objectives": [], "vod": null, "schedule": {"items": [{"id": "8bd6f377-f133-4875-81f1-1d63ecb7c2aa", "title": "Introduction", "start": "2024-10-05T13:15+02:00", "end": "2024-10-05T13:17+02:00", "speakers": {"items": []}, "vod": null}, {"id": "f18f88f1-9ca9-403f-8fa4-c0a555a75da3", "title": "Foie et pancréas en scanner : exemples pertinents sur le scanner à comptage photonique", "start": "2024-10-05T13:17+02:00", "end": "2024-10-05T13:25+02:00", "speakers": {"items": []}, "vod": null}, {"id": "8f8cfb2b-c8c2-41e4-a335-ec237b70d47a", "title": "Intérêt de l’IA pour la reconstruction d’images en IRM : applications en oncologie sur foie et pan", "start": "2024-10-05T13:25+02:00", "end": "2024-10-05T13:33+02:00", "speakers": {"items": []}, "vod": null}, {"id": "49542f6a-33f2-44a1-907f-67c10b6b3001", "title": "Foie en radiologie interventionnelle : de nouvelles avancées techniques pour de nouvelle possibilité", "start": "2024-10-05T13:33+02:00", "end": "2024-10-05T13:41+02:00", "speakers": {"items": []}, "vod": null}, {"id": "9ce1a602-9411-4a62-a126-383fc9ea550f", "title": "Questions/réponses", "start": "2024-10-05T13:41+02:00", "end": "2024-10-05T13:45+02:00", "speakers": {"items": []}, "vod": null}]}, "roles": [], "speakers": {"items": [{"firstName": "Charles", "lastName": "Roux", "roles": [{"name": "speaker"}], "photo": {"url": "https://services.y-congress.com/congress/wspreview/getphoto.aspx?idPhoto=177286&t=1"}, "city": {"name": "Paris"}, "country": {"name": "France"}}, {"firstName": "Shridevi", "lastName": "SANDIRAMOURTY", "roles": [{"name": "speaker"}], "photo": {"url": "https://services.y-congress.com/congress/wspreview/getphoto.aspx?idPhoto=177287&t=1"}, "city": {"name": "Paris"}, "country": {"name": "France"}}, {"firstName": "Valérie", "lastName": "Laurent", "roles": [{"name": "speaker"}], "photo": {"url": "https://services.y-congress.com/congress/wspreview/getphoto.aspx?idPhoto=177164&t=1"}, "city": {"name": "Nancy"}, "country": {"name": "France"}}, {"firstName": "Khalid", "lastName": "Ambarki", "roles": [{"name": "speaker"}], "photo": null, "city": {"name": "Saint-Denis"}, "country": {"name": "France"}}, {"firstName": "Serge", "lastName": "Ripart", "roles": [{"name": "speaker"}], "photo": null, "city": {"name": "Saint-Denis"}, "country": {"name": "France"}}, {"firstName": "Yves", "lastName": "Menu", "roles": [{"name": "speaker"}], "photo": {"url": "https://services.y-congress.com/congress/wspreview/getphoto.aspx?idPhoto=177463&t=1"}, "city": {"name": "Paris"}, "country": {"name": "France"}}, {"firstName": "Cédric", "lastName": "Croisille", "roles": [{"name": "speaker"}], "photo": {"url": "https://services.y-congress.com/congress/wspreview/getphoto.aspx?idPhoto=123644&t=1"}, "city": {"name": "Bordeaux"}, "country": {"name": "France"}}]}, "chairs": {"items": []}, "topics": [], "tracks": [], "organizers": [{"name": "Siemens Healthineers", "logo": null}], "programmeOwners": [{"title": "Agenda Partenaire"}]}}}